{
  "updated_at": "2026-04-07T04:03:47.462881+00:00",
  "customer_id": "5879952911",
  "period": {
    "start": "2026-01-07",
    "end": "2026-04-07"
  },
  "totals": {
    "impressions": 29005,
    "clicks": 8972,
    "cost": 3603.5066460000007,
    "conversions": 670.0,
    "ctr": 30.932597827960695,
    "cpc": 0.4016391714222025,
    "cost_per_conv": 5.37836812835821
  },
  "campaigns": [
    {
      "id": "23705408328",
      "name": "[LM] [GERAL] [PMAX] [FESTIVAL INTERLAGOS 2026] [31.03.26]",
      "status": "ENABLED",
      "impressions": 17938,
      "clicks": 5182,
      "cost": 1576.9918089999999,
      "conversions": 410.5,
      "ctr": 28.888393354889065,
      "cpc": 0.3043210746815901,
      "cost_per_conv": 3.8416365627283797
    },
    {
      "id": "23710366061",
      "name": "[LM] [GERAL] [PESQUI] [FESTIVAL INTERLAGOS 2026] [31.03.26]",
      "status": "ENABLED",
      "impressions": 4045,
      "clicks": 1971,
      "cost": 359.29296999999997,
      "conversions": 159.13636300000002,
      "ctr": 48.72682323856613,
      "cpc": 0.1822896854388635,
      "cost_per_conv": 2.2577678867777062
    },
    {
      "id": "23728271435",
      "name": "[LM] [AUTO PMAX] [FESTIVAL INTERLAGOS 2026]",
      "status": "ENABLED",
      "impressions": 1048,
      "clicks": 114,
      "cost": 117.63926000000001,
      "conversions": 2.0,
      "ctr": 10.877862595419847,
      "cpc": 1.0319233333333333,
      "cost_per_conv": 58.819630000000004
    },
    {
      "id": "23705094165",
      "name": "[LM] [MOTO] [PESQUI] [FESTIVAL INTERLAGOS 2026] [31.03.26]",
      "status": "ENABLED",
      "impressions": 4223,
      "clicks": 932,
      "cost": 774.190332,
      "conversions": 61.363637999999995,
      "ctr": 22.069618754439972,
      "cpc": 0.830676321888412,
      "cost_per_conv": 12.616434703561742
    },
    {
      "id": "23715183778",
      "name": "[LM] [AUTO] [PESQUI] [FESTIVAL INTERLAGOS 2026] [31.03.26]",
      "status": "ENABLED",
      "impressions": 1751,
      "clicks": 773,
      "cost": 775.392275,
      "conversions": 36.999999,
      "ctr": 44.14620217018847,
      "cpc": 1.0030947930142304,
      "cost_per_conv": 20.956548539366178
    }
  ],
  "daily_series": [
    {
      "date": "2026-03-31",
      "impressions": 801,
      "clicks": 416,
      "cost": 394.34171399999997,
      "conversions": 251.5
    },
    {
      "date": "2026-04-01",
      "impressions": 4392,
      "clicks": 2208,
      "cost": 834.0052400000001,
      "conversions": 180.5
    },
    {
      "date": "2026-04-02",
      "impressions": 4010,
      "clicks": 1508,
      "cost": 369.89813300000003,
      "conversions": 70.0
    },
    {
      "date": "2026-04-03",
      "impressions": 4001,
      "clicks": 1225,
      "cost": 410.37123299999996,
      "conversions": 70.0
    },
    {
      "date": "2026-04-04",
      "impressions": 3231,
      "clicks": 732,
      "cost": 373.956232,
      "conversions": 35.0
    },
    {
      "date": "2026-04-05",
      "impressions": 5971,
      "clicks": 1353,
      "cost": 466.943137,
      "conversions": 32.0
    },
    {
      "date": "2026-04-06",
      "impressions": 6527,
      "clicks": 1522,
      "cost": 748.9037940000001,
      "conversions": 31.0
    },
    {
      "date": "2026-04-07",
      "impressions": 72,
      "clicks": 8,
      "cost": 5.087163,
      "conversions": 0.0
    }
  ]
}