{
  "updated_at": "2026-04-22T20:36:04.428773+00:00",
  "customer_id": "5879952911",
  "period": {
    "start": "2026-01-22",
    "end": "2026-04-22"
  },
  "totals": {
    "impressions": 491670,
    "clicks": 26805,
    "cost": 23662.955439000016,
    "conversions": 1300.1900469999998,
    "ctr": 5.451827445237659,
    "cpc": 0.8827814004476783,
    "cost_per_conv": 18.199612813218234
  },
  "campaigns": [
    {
      "id": "23705094165",
      "name": "[LM] [MOTO] [PESQUI] [FESTIVAL INTERLAGOS 2026] [31.03.26]",
      "status": "PAUSED",
      "impressions": 6164,
      "clicks": 1157,
      "cost": 962.998218,
      "conversions": 81.61972800000001,
      "ctr": 18.770279039584686,
      "cpc": 0.8323234382022472,
      "cost_per_conv": 11.798596265843962
    },
    {
      "id": "23705408328",
      "name": "[LM] [GERAL] [PMAX] [FESTIVAL INTERLAGOS 2026] [31.03.26]",
      "status": "ENABLED",
      "impressions": 85753,
      "clicks": 12688,
      "cost": 9515.366670000001,
      "conversions": 747.5588480000001,
      "ctr": 14.795983813977355,
      "cpc": 0.749950084331652,
      "cost_per_conv": 12.728585442413223
    },
    {
      "id": "23710366061",
      "name": "[LM] [GERAL] [PESQUI] [FESTIVAL INTERLAGOS 2026] [31.03.26]",
      "status": "ENABLED",
      "impressions": 33051,
      "clicks": 8520,
      "cost": 6751.129382000001,
      "conversions": 365.73726300000004,
      "ctr": 25.77834256149587,
      "cpc": 0.7923860776995306,
      "cost_per_conv": 18.458959654871155
    },
    {
      "id": "23752829733",
      "name": "[LM] [NOVA DEMANDA FESTIVAL INTERLAGOS 2026]",
      "status": "ENABLED",
      "impressions": 257290,
      "clicks": 1531,
      "cost": 2847.417777,
      "conversions": 18.225211,
      "ctr": 0.5950483889774184,
      "cpc": 1.8598417877204443,
      "cost_per_conv": 156.23510624925
    },
    {
      "id": "23763602837",
      "name": "[LM] [RMKT] [FESTIVAL INTERLAGOS 2026]",
      "status": "ENABLED",
      "impressions": 28144,
      "clicks": 380,
      "cost": 591.398125,
      "conversions": 7.4613119999999995,
      "ctr": 1.3501989766913018,
      "cpc": 1.556310855263158,
      "cost_per_conv": 79.26194816675674
    },
    {
      "id": "23785828936",
      "name": "[LM] [MOTO] [PESQUI] [FESTIVAL INTERLAGOS 2026] [22.04.26]",
      "status": "ENABLED",
      "impressions": 2,
      "clicks": 0,
      "cost": 0.0,
      "conversions": 0.0,
      "ctr": 0.0,
      "cpc": 0,
      "cost_per_conv": 0
    },
    {
      "id": "23715183778",
      "name": "[LM] [AUTO] [PESQUI] [FESTIVAL INTERLAGOS 2026] [31.03.26]",
      "status": "PAUSED",
      "impressions": 7615,
      "clicks": 1446,
      "cost": 1637.994073,
      "conversions": 57.541664999999995,
      "ctr": 18.988837820091923,
      "cpc": 1.1327759840940526,
      "cost_per_conv": 28.46622656817456
    },
    {
      "id": "23728271435",
      "name": "[LM] [AUTO PMAX] [FESTIVAL INTERLAGOS 2026]",
      "status": "PAUSED",
      "impressions": 73651,
      "clicks": 1083,
      "cost": 1356.651194,
      "conversions": 22.04602,
      "ctr": 1.4704484664159345,
      "cpc": 1.2526788494921515,
      "cost_per_conv": 61.53723864897157
    }
  ],
  "daily_series": [
    {
      "date": "2026-03-31",
      "impressions": 801,
      "clicks": 416,
      "cost": 394.34171399999997,
      "conversions": 255.11661800000002
    },
    {
      "date": "2026-04-01",
      "impressions": 4392,
      "clicks": 2208,
      "cost": 834.0052400000001,
      "conversions": 194.932187
    },
    {
      "date": "2026-04-02",
      "impressions": 4010,
      "clicks": 1508,
      "cost": 369.89813300000003,
      "conversions": 83.472865
    },
    {
      "date": "2026-04-03",
      "impressions": 3936,
      "clicks": 1215,
      "cost": 408.551804,
      "conversions": 80.648746
    },
    {
      "date": "2026-04-04",
      "impressions": 3226,
      "clicks": 732,
      "cost": 373.956232,
      "conversions": 43.266755
    },
    {
      "date": "2026-04-05",
      "impressions": 5753,
      "clicks": 1310,
      "cost": 463.50226499999997,
      "conversions": 57.742835
    },
    {
      "date": "2026-04-06",
      "impressions": 6501,
      "clicks": 1519,
      "cost": 748.5456360000001,
      "conversions": 57.028469
    },
    {
      "date": "2026-04-07",
      "impressions": 16540,
      "clicks": 1071,
      "cost": 756.576909,
      "conversions": 43.703579
    },
    {
      "date": "2026-04-08",
      "impressions": 12496,
      "clicks": 966,
      "cost": 579.341441,
      "conversions": 41.993065
    },
    {
      "date": "2026-04-09",
      "impressions": 6387,
      "clicks": 951,
      "cost": 661.684085,
      "conversions": 39.620382
    },
    {
      "date": "2026-04-10",
      "impressions": 7287,
      "clicks": 1012,
      "cost": 761.406211,
      "conversions": 34.294572
    },
    {
      "date": "2026-04-11",
      "impressions": 17020,
      "clicks": 1167,
      "cost": 1481.769969,
      "conversions": 36.055366
    },
    {
      "date": "2026-04-12",
      "impressions": 26944,
      "clicks": 1440,
      "cost": 1575.1457889999997,
      "conversions": 46.890308000000005
    },
    {
      "date": "2026-04-13",
      "impressions": 28663,
      "clicks": 1091,
      "cost": 1077.7700610000002,
      "conversions": 33.127341
    },
    {
      "date": "2026-04-14",
      "impressions": 8399,
      "clicks": 886,
      "cost": 1152.1912699999998,
      "conversions": 34.278411999999996
    },
    {
      "date": "2026-04-15",
      "impressions": 6857,
      "clicks": 888,
      "cost": 1507.555783,
      "conversions": 35.577369
    },
    {
      "date": "2026-04-16",
      "impressions": 14160,
      "clicks": 1108,
      "cost": 1305.8104660000001,
      "conversions": 28.585338
    },
    {
      "date": "2026-04-17",
      "impressions": 71945,
      "clicks": 1612,
      "cost": 1671.150946,
      "conversions": 39.778166
    },
    {
      "date": "2026-04-18",
      "impressions": 102412,
      "clicks": 1435,
      "cost": 1951.766833,
      "conversions": 28.845191
    },
    {
      "date": "2026-04-19",
      "impressions": 50842,
      "clicks": 1261,
      "cost": 1552.36004,
      "conversions": 26.291406000000002
    },
    {
      "date": "2026-04-20",
      "impressions": 34354,
      "clicks": 1044,
      "cost": 1454.867321,
      "conversions": 36.616534
    },
    {
      "date": "2026-04-21",
      "impressions": 37133,
      "clicks": 1166,
      "cost": 1464.66921,
      "conversions": 14.544663
    },
    {
      "date": "2026-04-22",
      "impressions": 21612,
      "clicks": 799,
      "cost": 1116.0880809999999,
      "conversions": 7.7798799999999995
    }
  ]
}