{
  "updated_at": "2026-04-11T05:50:14.731317+00:00",
  "customer_id": "5879952911",
  "period": {
    "start": "2026-01-11",
    "end": "2026-04-11"
  },
  "totals": {
    "impressions": 71933,
    "clicks": 13000,
    "cost": 6396.503791,
    "conversions": 848.0,
    "ctr": 18.072372902562105,
    "cpc": 0.49203875315384615,
    "cost_per_conv": 7.543046923349057
  },
  "campaigns": [
    {
      "id": "23705408328",
      "name": "[LM] [GERAL] [PMAX] [FESTIVAL INTERLAGOS 2026] [31.03.26]",
      "status": "ENABLED",
      "impressions": 32305,
      "clicks": 7355,
      "cost": 2947.9128370000003,
      "conversions": 524.940881,
      "ctr": 22.767373471598823,
      "cpc": 0.40080392073419446,
      "cost_per_conv": 5.615704441582633
    },
    {
      "id": "23710366061",
      "name": "[LM] [GERAL] [PESQUI] [FESTIVAL INTERLAGOS 2026] [31.03.26]",
      "status": "ENABLED",
      "impressions": 9296,
      "clicks": 2922,
      "cost": 858.047185,
      "conversions": 185.772726,
      "ctr": 31.4328743545611,
      "cpc": 0.29365064510609173,
      "cost_per_conv": 4.618800635998634
    },
    {
      "id": "23715183778",
      "name": "[LM] [AUTO] [PESQUI] [FESTIVAL INTERLAGOS 2026] [31.03.26]",
      "status": "ENABLED",
      "impressions": 3344,
      "clicks": 1023,
      "cost": 1028.273919,
      "conversions": 46.999999,
      "ctr": 30.592105263157894,
      "cpc": 1.0051553460410556,
      "cost_per_conv": 21.878168954854658
    },
    {
      "id": "23728271435",
      "name": "[LM] [AUTO PMAX] [FESTIVAL INTERLAGOS 2026]",
      "status": "ENABLED",
      "impressions": 20809,
      "clicks": 509,
      "cost": 596.6753309999999,
      "conversions": 14.0,
      "ctr": 2.4460569945696573,
      "cpc": 1.1722501591355599,
      "cost_per_conv": 42.619666499999994
    },
    {
      "id": "23705094165",
      "name": "[LM] [MOTO] [PESQUI] [FESTIVAL INTERLAGOS 2026] [31.03.26]",
      "status": "ENABLED",
      "impressions": 6179,
      "clicks": 1191,
      "cost": 965.5945189999999,
      "conversions": 76.286394,
      "ctr": 19.27496358634083,
      "cpc": 0.8107426691855583,
      "cost_per_conv": 12.657493274619847
    }
  ],
  "daily_series": [
    {
      "date": "2026-03-31",
      "impressions": 801,
      "clicks": 416,
      "cost": 394.34171399999997,
      "conversions": 252.5
    },
    {
      "date": "2026-04-01",
      "impressions": 4392,
      "clicks": 2208,
      "cost": 834.0052400000001,
      "conversions": 188.733248
    },
    {
      "date": "2026-04-02",
      "impressions": 4010,
      "clicks": 1508,
      "cost": 369.89813300000003,
      "conversions": 75.5
    },
    {
      "date": "2026-04-03",
      "impressions": 4001,
      "clicks": 1225,
      "cost": 410.37123299999996,
      "conversions": 76.391774
    },
    {
      "date": "2026-04-04",
      "impressions": 3231,
      "clicks": 732,
      "cost": 373.956232,
      "conversions": 39.0
    },
    {
      "date": "2026-04-05",
      "impressions": 5970,
      "clicks": 1352,
      "cost": 466.64713900000004,
      "conversions": 48.19482
    },
    {
      "date": "2026-04-06",
      "impressions": 6527,
      "clicks": 1522,
      "cost": 748.9037940000001,
      "conversions": 49.5
    },
    {
      "date": "2026-04-07",
      "impressions": 16540,
      "clicks": 1071,
      "cost": 756.586909,
      "conversions": 36.666666
    },
    {
      "date": "2026-04-08",
      "impressions": 12498,
      "clicks": 967,
      "cost": 579.354798,
      "conversions": 32.905266
    },
    {
      "date": "2026-04-09",
      "impressions": 6387,
      "clicks": 951,
      "cost": 661.684085,
      "conversions": 30.608226000000002
    },
    {
      "date": "2026-04-10",
      "impressions": 7285,
      "clicks": 1011,
      "cost": 761.01268,
      "conversions": 17.666666
    },
    {
      "date": "2026-04-11",
      "impressions": 291,
      "clicks": 37,
      "cost": 39.741834000000004,
      "conversions": 0.333334
    }
  ]
}