{
  "updated_at": "2026-04-13T19:40:22.735675+00:00",
  "customer_id": "5879952911",
  "period": {
    "start": "2026-01-13",
    "end": "2026-04-13"
  },
  "totals": {
    "impressions": 130994,
    "clicks": 16242,
    "cost": 10085.764252000004,
    "conversions": 946.190047,
    "ctr": 12.39904117745851,
    "cpc": 0.6209681228912698,
    "cost_per_conv": 10.659342997718094
  },
  "campaigns": [
    {
      "id": "23705094165",
      "name": "[LM] [MOTO] [PESQUI] [FESTIVAL INTERLAGOS 2026] [31.03.26]",
      "status": "ENABLED",
      "impressions": 6240,
      "clicks": 1199,
      "cost": 967.0136559999999,
      "conversions": 79.61972800000001,
      "ctr": 19.21474358974359,
      "cpc": 0.8065168106755628,
      "cost_per_conv": 12.145402656989733
    },
    {
      "id": "23705408328",
      "name": "[LM] [GERAL] [PMAX] [FESTIVAL INTERLAGOS 2026] [31.03.26]",
      "status": "ENABLED",
      "impressions": 42635,
      "clicks": 8708,
      "cost": 4663.181651000001,
      "conversions": 578.940881,
      "ctr": 20.424533833704704,
      "cpc": 0.5355054720946257,
      "cost_per_conv": 8.0546767451373
    },
    {
      "id": "23710366061",
      "name": "[LM] [GERAL] [PESQUI] [FESTIVAL INTERLAGOS 2026] [31.03.26]",
      "status": "ENABLED",
      "impressions": 14982,
      "clicks": 4009,
      "cost": 1729.5411649999999,
      "conversions": 218.272726,
      "ctr": 26.758777199305833,
      "cpc": 0.4314146083811424,
      "cost_per_conv": 7.923762151575455
    },
    {
      "id": "23715183778",
      "name": "[LM] [AUTO] [PESQUI] [FESTIVAL INTERLAGOS 2026] [31.03.26]",
      "status": "ENABLED",
      "impressions": 6258,
      "clicks": 1340,
      "cost": 1480.977619,
      "conversions": 53.166664999999995,
      "ctr": 21.41259188239054,
      "cpc": 1.105207178358209,
      "cost_per_conv": 27.85537928700249
    },
    {
      "id": "23728271435",
      "name": "[LM] [AUTO PMAX] [FESTIVAL INTERLAGOS 2026]",
      "status": "ENABLED",
      "impressions": 60879,
      "clicks": 986,
      "cost": 1245.0501610000001,
      "conversions": 16.190047,
      "ctr": 1.6196061039110365,
      "cpc": 1.2627283580121704,
      "cost_per_conv": 76.9021955896731
    }
  ],
  "daily_series": [
    {
      "date": "2026-03-31",
      "impressions": 801,
      "clicks": 416,
      "cost": 394.34171399999997,
      "conversions": 252.5
    },
    {
      "date": "2026-04-01",
      "impressions": 4392,
      "clicks": 2208,
      "cost": 834.0052400000001,
      "conversions": 188.733248
    },
    {
      "date": "2026-04-02",
      "impressions": 4010,
      "clicks": 1508,
      "cost": 369.89813300000003,
      "conversions": 76.28876
    },
    {
      "date": "2026-04-03",
      "impressions": 4001,
      "clicks": 1225,
      "cost": 410.37123299999996,
      "conversions": 78.398746
    },
    {
      "date": "2026-04-04",
      "impressions": 3231,
      "clicks": 732,
      "cost": 373.956232,
      "conversions": 43.0
    },
    {
      "date": "2026-04-05",
      "impressions": 5970,
      "clicks": 1352,
      "cost": 466.64713900000004,
      "conversions": 50.19482
    },
    {
      "date": "2026-04-06",
      "impressions": 6527,
      "clicks": 1522,
      "cost": 748.9037940000001,
      "conversions": 51.5
    },
    {
      "date": "2026-04-07",
      "impressions": 16540,
      "clicks": 1071,
      "cost": 756.576909,
      "conversions": 38.666666
    },
    {
      "date": "2026-04-08",
      "impressions": 12496,
      "clicks": 966,
      "cost": 579.341441,
      "conversions": 36.095313
    },
    {
      "date": "2026-04-09",
      "impressions": 6387,
      "clicks": 951,
      "cost": 661.684085,
      "conversions": 36.608226
    },
    {
      "date": "2026-04-10",
      "impressions": 7287,
      "clicks": 1012,
      "cost": 761.406211,
      "conversions": 30.877906
    },
    {
      "date": "2026-04-11",
      "impressions": 17021,
      "clicks": 1167,
      "cost": 1481.771846,
      "conversions": 28.666667
    },
    {
      "date": "2026-04-12",
      "impressions": 26943,
      "clicks": 1441,
      "cost": 1575.1598409999997,
      "conversions": 23.659695
    },
    {
      "date": "2026-04-13",
      "impressions": 15388,
      "clicks": 671,
      "cost": 671.700434,
      "conversions": 11.0
    }
  ]
}