{
  "updated_at": "2026-04-12T09:02:20.990375+00:00",
  "customer_id": "5879952911",
  "period": {
    "start": "2026-01-12",
    "end": "2026-04-12"
  },
  "totals": {
    "impressions": 91367,
    "clicks": 14205,
    "cost": 7959.517381000001,
    "conversions": 882.1900469999999,
    "ctr": 15.54718880996421,
    "cpc": 0.5603320929954242,
    "cost_per_conv": 9.022452030679055
  },
  "campaigns": [
    {
      "id": "23705408328",
      "name": "[LM] [GERAL] [PMAX] [FESTIVAL INTERLAGOS 2026] [31.03.26]",
      "status": "ENABLED",
      "impressions": 37447,
      "clicks": 8063,
      "cost": 3863.422525,
      "conversions": 546.940881,
      "ctr": 21.53176489438406,
      "cpc": 0.47915447414113854,
      "cost_per_conv": 7.0636930959271265
    },
    {
      "id": "23710366061",
      "name": "[LM] [GERAL] [PESQUI] [FESTIVAL INTERLAGOS 2026] [31.03.26]",
      "status": "ENABLED",
      "impressions": 10477,
      "clicks": 3108,
      "cost": 1022.7737640000001,
      "conversions": 193.272726,
      "ctr": 29.66498043333015,
      "cpc": 0.3290777876447877,
      "cost_per_conv": 5.291868051780882
    },
    {
      "id": "23715183778",
      "name": "[LM] [AUTO] [PESQUI] [FESTIVAL INTERLAGOS 2026] [31.03.26]",
      "status": "ENABLED",
      "impressions": 4312,
      "clicks": 1112,
      "cost": 1150.670838,
      "conversions": 50.166664999999995,
      "ctr": 25.788497217068645,
      "cpc": 1.0347759334532374,
      "cost_per_conv": 22.936960987938907
    },
    {
      "id": "23728271435",
      "name": "[LM] [AUTO PMAX] [FESTIVAL INTERLAGOS 2026]",
      "status": "ENABLED",
      "impressions": 32930,
      "clicks": 728,
      "cost": 956.4137089999999,
      "conversions": 15.190047,
      "ctr": 2.2107500759186154,
      "cpc": 1.3137550947802197,
      "cost_per_conv": 62.96318299739296
    },
    {
      "id": "23705094165",
      "name": "[LM] [MOTO] [PESQUI] [FESTIVAL INTERLAGOS 2026] [31.03.26]",
      "status": "ENABLED",
      "impressions": 6201,
      "clicks": 1194,
      "cost": 966.2365449999999,
      "conversions": 76.61972800000001,
      "ctr": 19.254958877600387,
      "cpc": 0.8092433375209379,
      "cost_per_conv": 12.6108062534495
    }
  ],
  "daily_series": [
    {
      "date": "2026-03-31",
      "impressions": 801,
      "clicks": 416,
      "cost": 394.34171399999997,
      "conversions": 252.5
    },
    {
      "date": "2026-04-01",
      "impressions": 4392,
      "clicks": 2208,
      "cost": 834.0052400000001,
      "conversions": 188.733248
    },
    {
      "date": "2026-04-02",
      "impressions": 4010,
      "clicks": 1508,
      "cost": 369.89813300000003,
      "conversions": 75.5
    },
    {
      "date": "2026-04-03",
      "impressions": 4001,
      "clicks": 1225,
      "cost": 410.37123299999996,
      "conversions": 77.391774
    },
    {
      "date": "2026-04-04",
      "impressions": 3231,
      "clicks": 732,
      "cost": 373.956232,
      "conversions": 43.0
    },
    {
      "date": "2026-04-05",
      "impressions": 5970,
      "clicks": 1352,
      "cost": 466.64713900000004,
      "conversions": 49.19482
    },
    {
      "date": "2026-04-06",
      "impressions": 6527,
      "clicks": 1522,
      "cost": 748.9037940000001,
      "conversions": 50.5
    },
    {
      "date": "2026-04-07",
      "impressions": 16540,
      "clicks": 1070,
      "cost": 756.576909,
      "conversions": 36.666666
    },
    {
      "date": "2026-04-08",
      "impressions": 12496,
      "clicks": 966,
      "cost": 579.341441,
      "conversions": 33.095313000000004
    },
    {
      "date": "2026-04-09",
      "impressions": 6387,
      "clicks": 951,
      "cost": 661.684085,
      "conversions": 33.608226
    },
    {
      "date": "2026-04-10",
      "impressions": 7287,
      "clicks": 1012,
      "cost": 761.431509,
      "conversions": 21.666666
    },
    {
      "date": "2026-04-11",
      "impressions": 17021,
      "clicks": 1166,
      "cost": 1481.769598,
      "conversions": 20.333334
    },
    {
      "date": "2026-04-12",
      "impressions": 2704,
      "clicks": 77,
      "cost": 120.59035400000002,
      "conversions": 0.0
    }
  ]
}