{
  "updated_at": "2026-04-16T06:18:19.829867+00:00",
  "customer_id": "5879952911",
  "period": {
    "start": "2026-01-16",
    "end": "2026-04-16"
  },
  "totals": {
    "impressions": 160575,
    "clicks": 18462,
    "cost": 13203.595864,
    "conversions": 1049.190047,
    "ctr": 11.497431106959365,
    "cpc": 0.7151768965442531,
    "cost_per_conv": 12.584560730206775
  },
  "campaigns": [
    {
      "id": "23705408328",
      "name": "[LM] [GERAL] [PMAX] [FESTIVAL INTERLAGOS 2026] [31.03.26]",
      "status": "ENABLED",
      "impressions": 53509,
      "clicks": 9704,
      "cost": 6098.0568299999995,
      "conversions": 637.9324790000001,
      "ctr": 18.13526696443589,
      "cpc": 0.6284065158697444,
      "cost_per_conv": 9.559094466485064
    },
    {
      "id": "23710366061",
      "name": "[LM] [GERAL] [PESQUI] [FESTIVAL INTERLAGOS 2026] [31.03.26]",
      "status": "ENABLED",
      "impressions": 19521,
      "clicks": 5028,
      "cost": 3143.4842280000003,
      "conversions": 257.89772600000003,
      "ctr": 25.756877209159367,
      "cpc": 0.6251957494033413,
      "cost_per_conv": 12.188879199345868
    },
    {
      "id": "23752829733",
      "name": "[LM] [NOVA DEMANDA FESTIVAL INTERLAGOS 2026]",
      "status": "ENABLED",
      "impressions": 22,
      "clicks": 0,
      "cost": 0.20588299999999998,
      "conversions": 0.0,
      "ctr": 0.0,
      "cpc": 0,
      "cost_per_conv": 0
    },
    {
      "id": "23705094165",
      "name": "[LM] [MOTO] [PESQUI] [FESTIVAL INTERLAGOS 2026] [31.03.26]",
      "status": "PAUSED",
      "impressions": 6257,
      "clicks": 1201,
      "cost": 967.2036559999999,
      "conversions": 79.61972800000001,
      "ctr": 19.194502157583507,
      "cpc": 0.8053319367194004,
      "cost_per_conv": 12.147789000233708
    },
    {
      "id": "23715183778",
      "name": "[LM] [AUTO] [PESQUI] [FESTIVAL INTERLAGOS 2026] [31.03.26]",
      "status": "PAUSED",
      "impressions": 7615,
      "clicks": 1446,
      "cost": 1637.994073,
      "conversions": 55.541664999999995,
      "ctr": 18.988837820091923,
      "cpc": 1.1327759840940526,
      "cost_per_conv": 29.49126701549189
    },
    {
      "id": "23728271435",
      "name": "[LM] [AUTO PMAX] [FESTIVAL INTERLAGOS 2026]",
      "status": "PAUSED",
      "impressions": 73651,
      "clicks": 1083,
      "cost": 1356.651194,
      "conversions": 18.198449,
      "ctr": 1.4704484664159345,
      "cpc": 1.2526788494921515,
      "cost_per_conv": 74.54762732802119
    }
  ],
  "daily_series": [
    {
      "date": "2026-03-31",
      "impressions": 801,
      "clicks": 416,
      "cost": 394.34171399999997,
      "conversions": 253.5
    },
    {
      "date": "2026-04-01",
      "impressions": 4392,
      "clicks": 2208,
      "cost": 834.0052400000001,
      "conversions": 188.733248
    },
    {
      "date": "2026-04-02",
      "impressions": 4010,
      "clicks": 1508,
      "cost": 369.89813300000003,
      "conversions": 79.28876
    },
    {
      "date": "2026-04-03",
      "impressions": 4001,
      "clicks": 1225,
      "cost": 410.37123299999996,
      "conversions": 80.648746
    },
    {
      "date": "2026-04-04",
      "impressions": 3231,
      "clicks": 732,
      "cost": 373.956232,
      "conversions": 43.0
    },
    {
      "date": "2026-04-05",
      "impressions": 5970,
      "clicks": 1352,
      "cost": 466.64713900000004,
      "conversions": 52.44482
    },
    {
      "date": "2026-04-06",
      "impressions": 6527,
      "clicks": 1522,
      "cost": 748.9037940000001,
      "conversions": 51.5
    },
    {
      "date": "2026-04-07",
      "impressions": 16540,
      "clicks": 1071,
      "cost": 756.576909,
      "conversions": 40.666666
    },
    {
      "date": "2026-04-08",
      "impressions": 12496,
      "clicks": 966,
      "cost": 579.341441,
      "conversions": 40.435617
    },
    {
      "date": "2026-04-09",
      "impressions": 6387,
      "clicks": 951,
      "cost": 661.684085,
      "conversions": 37.620382
    },
    {
      "date": "2026-04-10",
      "impressions": 7287,
      "clicks": 1012,
      "cost": 761.406211,
      "conversions": 31.127906
    },
    {
      "date": "2026-04-11",
      "impressions": 17020,
      "clicks": 1167,
      "cost": 1481.769969,
      "conversions": 33.666667000000004
    },
    {
      "date": "2026-04-12",
      "impressions": 26944,
      "clicks": 1440,
      "cost": 1575.1457889999997,
      "conversions": 40.671851000000004
    },
    {
      "date": "2026-04-13",
      "impressions": 28663,
      "clicks": 1091,
      "cost": 1077.7700610000002,
      "conversions": 30.640823
    },
    {
      "date": "2026-04-14",
      "impressions": 8399,
      "clicks": 886,
      "cost": 1152.19783,
      "conversions": 17.68715
    },
    {
      "date": "2026-04-15",
      "impressions": 6862,
      "clicks": 888,
      "cost": 1507.3544769999999,
      "conversions": 26.557411000000002
    },
    {
      "date": "2026-04-16",
      "impressions": 1045,
      "clicks": 27,
      "cost": 52.225607000000004,
      "conversions": 1.0
    }
  ]
}